<?xml version="1.0" encoding="UTF-8"?>
<as:AppSchemaDataAccess xmlns:as="http://www.geotools.org/app-schema"
    xmlns:ogc="http://www.opengis.net/ogc" xmlns:xs="http://www.w3.org/2001/XMLSchema" xmlns:xsi="http://www.w3.org/2001/XMLSchema-instance"
    xsi:schemaLocation="http://www.geotools.org/app-schema AppSchemaDataAccess.xsd">
    <namespaces>
		<Namespace>
			<prefix>aasg</prefix>
			<uri>SCHEMA_URI</uri>
		</Namespace>
		<Namespace>
            		<prefix>gml</prefix>
            		<uri>http://www.opengis.net/gml</uri>
        	</Namespace>
    </namespaces>
    <sourceDataStores>
		 <DataStore>
			<id>LAYER_NAMEDataStore</id>
			<parameters>
				<Parameter>
					<name>dbtype</name>
					<value>postgis</value>
				</Parameter>
				<Parameter>
					<name>host</name>
					<value>kyanite</value>
				</Parameter>
				<Parameter>
					<name>port</name>
					<value>5432</value>
				</Parameter>
				<Parameter>
					<name>database</name>
					<value>azgs</value>
				</Parameter>
				<Parameter>
					<name>schema</name>
					<value>sde</value>
				</Parameter>
				<Parameter>
					<name>user</name>
					<value>sde</value>
				</Parameter>
				<Parameter>
					<name>passwd</name>
					<value>XXXXXX</value>
				</Parameter>
			</parameters>
		</DataStore>
    </sourceDataStores>
    <targetTypes>
      <FeatureType>
        <schemaUri>SCHEMA_URI</schemaUri>
      </FeatureType>
    </targetTypes>
    <typeMappings>
		<FeatureTypeMapping>
			<sourceDataStore>LAYER_NAMEDataStore</sourceDataStore>
			<sourceType>XXXXXX</sourceType>
			<targetElement>aasg:LAYER_NAME</targetElement>
			<attributeMappings>
				<AttributeMapping>
					<targetAttribute>aasg:LAYER_NAME</targetAttribute>
					<idExpression><OCQL>getId()</OCQL></idExpression>
				</AttributeMapping>
			</attributeMappings>
    </FeatureTypeMapping>	
    </typeMappings>
</as:AppSchemaDataAccess>
